mcp_scientific_calculator/__init__.py
mcp_scientific_calculator/__main__.py
mcp_scientific_calculator/calculator.py
mcp_scientific_calculator/mcp_server.py
mcp_scientific_calculator-1.0.1.dist-info/licenses/LICENSE
mcp_scientific_calculator-1.0.1.dist-info/METADATA
mcp_scientific_calculator-1.0.1.dist-info/WHEEL
mcp_scientific_calculator-1.0.1.dist-info/entry_points.txt
mcp_scientific_calculator-1.0.1.dist-info/top_level.txt
mcp_scientific_calculator-1.0.1.dist-info/RECORD
