Metadata-Version: 2.4
Name: mcp-scientific-calculator
Version: 1.0.1
Summary: Production-ready Model Context Protocol server for advanced mathematical calculations (SymPy, NumPy, SciPy, pandas)
Author-email: MCP Calculator Team <lucyjohn@example.com>
License: MIT
Project-URL: Homepage, https://github.com/thinkitpossible/CalcMCP
Project-URL: Documentation, https://github.com/thinkitpossible/CalcMCP#readme
Project-URL: Repository, https://github.com/thinkitpossible/CalcMCP
Project-URL: Issues, https://github.com/thinkitpossible/CalcMCP/issues
Project-URL: Bug Reports, https://github.com/thinkitpossible/CalcMCP/issues
Project-URL: Source Code, https://github.com/thinkitpossible/CalcMCP
Keywords: mcp,model-context-protocol,calculator,math,sympy,numpy,scipy,pandas,scientific-computing
Classifier: Development Status :: 5 - Production/Stable
Classifier: Intended Audience :: Developers
Classifier: Intended Audience :: Science/Research
Classifier: License :: OSI Approved :: MIT License
Classifier: Programming Language :: Python :: 3
Classifier: Programming Language :: Python :: 3.8
Classifier: Programming Language :: Python :: 3.9
Classifier: Programming Language :: Python :: 3.10
Classifier: Programming Language :: Python :: 3.11
Classifier: Programming Language :: Python :: 3.12
Classifier: Topic :: Scientific/Engineering :: Mathematics
Classifier: Topic :: Software Development :: Libraries :: Python Modules
Requires-Python: >=3.8
License-File: LICENSE
Requires-Dist: sympy>=1.12
Requires-Dist: numpy>=1.24.0
Requires-Dist: scipy>=1.10.0
Requires-Dist: pandas>=2.0.0
Provides-Extra: dev
Requires-Dist: pytest>=7.0; extra == "dev"
Requires-Dist: black>=23.0; extra == "dev"
Requires-Dist: mypy>=1.0; extra == "dev"
Dynamic: license-file
